geopolars/convert.py
geopolars/geopolars.pyd
geopolars/py.typed
geopolars/__init__.py
geopolars/datasets/naturalearth_cities.arrow
geopolars/datasets/naturalearth_lowres.arrow
geopolars/datasets/nybb.arrow
geopolars/datasets/README.md
geopolars/datasets/__init__.py
geopolars/internals/geodataframe.py
geopolars/internals/geoseries.py
geopolars/internals/types.py
geopolars/internals/__init__.py
geopolars/io/file.py
geopolars/io/__init__.py
geopolars/proj/__init__.py
geopolars/proj_data/CH
geopolars/proj_data/copyright
geopolars/proj_data/deformation_model.schema.json
geopolars/proj_data/GL27
geopolars/proj_data/ITRF2000
geopolars/proj_data/ITRF2008
geopolars/proj_data/ITRF2014
geopolars/proj_data/nad.lst
geopolars/proj_data/nad27
geopolars/proj_data/nad83
geopolars/proj_data/other.extra
geopolars/proj_data/proj-config-version.cmake
geopolars/proj_data/proj-config.cmake
geopolars/proj_data/proj-targets-debug.cmake
geopolars/proj_data/proj-targets-release.cmake
geopolars/proj_data/proj-targets.cmake
geopolars/proj_data/proj.db
geopolars/proj_data/proj.ini
geopolars/proj_data/proj4-targets-debug.cmake
geopolars/proj_data/proj4-targets-release.cmake
geopolars/proj_data/proj4-targets.cmake
geopolars/proj_data/projjson.schema.json
geopolars/proj_data/triangulation.schema.json
geopolars/proj_data/usage
geopolars/proj_data/vcpkg.spdx.json
geopolars/proj_data/vcpkg_abi_info.txt
geopolars/proj_data/world
geopolars-0.1.0a4.dist-info/DELVEWHEEL
geopolars-0.1.0a4.dist-info/METADATA
geopolars-0.1.0a4.dist-info/RECORD
geopolars-0.1.0a4.dist-info/WHEEL
geopolars.libs/.load-order-geopolars-0.1.0a4
geopolars.libs/jpeg62-8a8c7af0a975c2e8a416804f5616a0fd.dll
geopolars.libs/libcurl-ab9e2a70d258e43d3ba8a8b737d5da29.dll
geopolars.libs/liblzma-d0207e0e9da32ef97fe0787fcd014694.dll
geopolars.libs/msvcp140.dll
geopolars.libs/proj-54a54b1c3d2f6d1ad0c0383b5d8d2b83.dll
geopolars.libs/sqlite3-d0510eb8e351b3de0b8aceb4c3635651.dll
geopolars.libs/tiff-250e8eab30fbdb8b674640c6df82f146.dll
geopolars.libs/vcruntime140.dll
geopolars.libs/vcruntime140_1.dll
